PirxcyPinger/__init__.py
SHINFNBOTS-5.1.0.dist-info/METADATA
SHINFNBOTS-5.1.0.dist-info/WHEEL
SHINFNBOTS-5.1.0.dist-info/top_level.txt
SHINFNBOTS-5.1.0.dist-info/RECORD
