Metadata-Version: 2.1
Name: SHINFNBOTS
Version: 5.1.0
Summary: FNBOTS
Home-page: https://pirxcypingerfinal.pirxcy1942.repl.co/
Author: SHIN
Classifier: Programming Language :: Python :: 3
Classifier: License :: OSI Approved :: MIT License
Classifier: Operating System :: OS Independent
Requires-Dist: aiohttp
